tests
print_r
