Metadata-Version: 1.0
Name: print-r
Version: 0.1.2
Summary: php print_r for python
Home-page: http://wiki.github.com/marcbelmont/python-print_r
Author: Marc Belmont
Author-email: code-marcbelmont-com
License: UNKNOWN
Keywords: php print_r
Platform: UNKNOWN
Classifier: Programming Language :: Python
Classifier: Topic :: Software Development :: Libraries :: Python Modules
